{
  "terminology": "SNOMEDCT_US",
  "version": "2024-07-01",
  "source": "curated-from-snomed-browser",
  "fetched_at": "2026-06-06",
  "concepts": [
    {
      "code": "72696002",
      "name": "Knee region structure",
      "pref_label": "Knee Region",
      "type": "body_region",
      "parents": [],
      "part_of": []
    },
    {
      "code": "49076000",
      "name": "Knee joint structure",
      "pref_label": "Knee Joint",
      "type": "joint",
      "parents": [
        "72696002"
      ],
      "part_of": [
        "72696002"
      ]
    },
    {
      "code": "57714003",
      "name": "Patellofemoral joint structure",
      "pref_label": "Patellofemoral Joint",
      "type": "joint",
      "parents": [
        "49076000"
      ],
      "part_of": [
        "49076000",
        "72696002"
      ]
    },
    {
      "code": "182204001",
      "name": "Tibiofemoral joint",
      "pref_label": "Tibiofemoral Joint",
      "type": "joint",
      "parents": [
        "49076000"
      ],
      "part_of": [
        "49076000",
        "72696002"
      ]
    },
    {
      "code": "75053002",
      "name": "Structure of patella",
      "pref_label": "Patella",
      "type": "bone",
      "parents": [
        "72696002"
      ],
      "part_of": [
        "72696002"
      ]
    },
    {
      "code": "59440001",
      "name": "Structure of medial meniscus",
      "pref_label": "Medial Meniscus",
      "type": "cartilage",
      "parents": [
        "49076000"
      ],
      "part_of": [
        "49076000",
        "72696002"
      ]
    },
    {
      "code": "64927001",
      "name": "Structure of lateral meniscus",
      "pref_label": "Lateral Meniscus",
      "type": "cartilage",
      "parents": [
        "49076000"
      ],
      "part_of": [
        "49076000",
        "72696002"
      ]
    },
    {
      "code": "20453009",
      "name": "Structure of anterior cruciate ligament",
      "pref_label": "Anterior Cruciate Ligament",
      "type": "ligament",
      "parents": [
        "49076000"
      ],
      "part_of": [
        "49076000",
        "72696002"
      ]
    },
    {
      "code": "13417002",
      "name": "Structure of posterior cruciate ligament of knee joint",
      "pref_label": "Posterior Cruciate Ligament",
      "type": "ligament",
      "parents": [
        "49076000"
      ],
      "part_of": [
        "49076000",
        "72696002"
      ]
    },
    {
      "code": "36117003",
      "name": "Structure of patellar ligament",
      "pref_label": "Patellar Tendon",
      "type": "tendon",
      "parents": [
        "72696002"
      ],
      "part_of": [
        "72696002"
      ]
    },
    {
      "code": "71341001",
      "name": "Structure of quadriceps femoris muscle",
      "pref_label": "Quadriceps Femoris",
      "type": "muscle",
      "parents": [
        "72696002"
      ],
      "part_of": [
        "72696002"
      ]
    },
    {
      "code": "88225001",
      "name": "Structure of hamstring muscles",
      "pref_label": "Hamstrings",
      "type": "muscle",
      "parents": [
        "72696002"
      ],
      "part_of": [
        "72696002"
      ]
    }
  ],
  "injury_concepts": [
    {
      "code": "57773001",
      "name": "Patellofemoral pain syndrome",
      "pref_label": "Patellofemoral Pain Syndrome",
      "alt_labels": [
        "PFPS",
        "runner's knee",
        "anterior knee pain"
      ],
      "involves": [
        "57714003",
        "72696002"
      ]
    },
    {
      "code": "444798002",
      "name": "Injury of anterior cruciate ligament",
      "pref_label": "ACL Tear",
      "alt_labels": [
        "ACL injury",
        "anterior cruciate ligament rupture",
        "ACL rupture"
      ],
      "involves": [
        "20453009",
        "49076000"
      ]
    },
    {
      "code": "444182009",
      "name": "Injury of meniscus of knee",
      "pref_label": "Meniscus Tear",
      "alt_labels": [
        "meniscal tear",
        "torn meniscus"
      ],
      "involves": [
        "59440001",
        "64927001",
        "49076000"
      ]
    },
    {
      "code": "29857009",
      "name": "Patellar tendinitis",
      "pref_label": "Patellar Tendinopathy",
      "alt_labels": [
        "jumper's knee",
        "patellar tendinitis"
      ],
      "involves": [
        "36117003",
        "72696002"
      ]
    },
    {
      "code": "43208000",
      "name": "Iliotibial band syndrome",
      "pref_label": "IT Band Syndrome",
      "alt_labels": [
        "ITBS",
        "runner's knee lateral",
        "iliotibial band friction"
      ],
      "involves": [
        "72696002"
      ]
    }
  ],
  "edges": [
    {
      "from": "49076000",
      "to": "72696002",
      "relation": "part-of"
    },
    {
      "from": "57714003",
      "to": "49076000",
      "relation": "part-of"
    },
    {
      "from": "57714003",
      "to": "72696002",
      "relation": "part-of"
    },
    {
      "from": "182204001",
      "to": "49076000",
      "relation": "part-of"
    },
    {
      "from": "182204001",
      "to": "72696002",
      "relation": "part-of"
    },
    {
      "from": "20453009",
      "to": "49076000",
      "relation": "part-of"
    },
    {
      "from": "20453009",
      "to": "72696002",
      "relation": "part-of"
    },
    {
      "from": "75053002",
      "to": "72696002",
      "relation": "part-of"
    },
    {
      "from": "59440001",
      "to": "49076000",
      "relation": "part-of"
    },
    {
      "from": "59440001",
      "to": "72696002",
      "relation": "part-of"
    },
    {
      "from": "64927001",
      "to": "49076000",
      "relation": "part-of"
    },
    {
      "from": "64927001",
      "to": "72696002",
      "relation": "part-of"
    },
    {
      "from": "13417002",
      "to": "49076000",
      "relation": "part-of"
    },
    {
      "from": "13417002",
      "to": "72696002",
      "relation": "part-of"
    },
    {
      "from": "36117003",
      "to": "72696002",
      "relation": "part-of"
    },
    {
      "from": "71341001",
      "to": "72696002",
      "relation": "part-of"
    },
    {
      "from": "88225001",
      "to": "72696002",
      "relation": "part-of"
    },
    {
      "from": "57773001",
      "to": "57714003",
      "relation": "involves"
    },
    {
      "from": "57773001",
      "to": "72696002",
      "relation": "involves"
    },
    {
      "from": "444798002",
      "to": "20453009",
      "relation": "involves"
    },
    {
      "from": "444798002",
      "to": "49076000",
      "relation": "involves"
    },
    {
      "from": "444182009",
      "to": "59440001",
      "relation": "involves"
    },
    {
      "from": "444182009",
      "to": "64927001",
      "relation": "involves"
    },
    {
      "from": "444182009",
      "to": "49076000",
      "relation": "involves"
    },
    {
      "from": "29857009",
      "to": "36117003",
      "relation": "involves"
    },
    {
      "from": "29857009",
      "to": "72696002",
      "relation": "involves"
    },
    {
      "from": "43208000",
      "to": "72696002",
      "relation": "involves"
    }
  ],
  "lumbar_concepts": [
    {
      "code": "122496007",
      "name": "Lumbar spine structure",
      "pref_label": "Lumbar Spine",
      "type": "body_region",
      "parents": [],
      "part_of": []
    },
    {
      "code": "297179000",
      "name": "Lumbar intervertebral joint structure",
      "pref_label": "Lumbar Intervertebral Joint",
      "type": "joint",
      "parents": [
        "122496007"
      ],
      "part_of": [
        "122496007"
      ]
    },
    {
      "code": "11944003",
      "name": "Structure of lumbar vertebra",
      "pref_label": "Lumbar Vertebra",
      "type": "bone",
      "parents": [
        "122496007"
      ],
      "part_of": [
        "122496007"
      ]
    },
    {
      "code": "46467000",
      "name": "Structure of erector spinae muscle",
      "pref_label": "Erector Spinae",
      "type": "muscle",
      "parents": [
        "122496007"
      ],
      "part_of": [
        "122496007"
      ]
    },
    {
      "code": "244944005",
      "name": "Structure of lumbar intervertebral disc",
      "pref_label": "Lumbar Intervertebral Disc",
      "type": "cartilage",
      "parents": [
        "122496007"
      ],
      "part_of": [
        "122496007"
      ]
    },
    {
      "code": "77736006",
      "name": "Structure of multifidus muscle",
      "pref_label": "Multifidus",
      "type": "muscle",
      "parents": [
        "122496007"
      ],
      "part_of": [
        "122496007"
      ]
    }
  ],
  "lumbar_injury_concepts": [
    {
      "code": "279039007",
      "name": "Low back pain",
      "pref_label": "Low Back Pain",
      "alt_labels": [
        "mechanical low back pain",
        "lumbar pain",
        "LBP",
        "lumbago"
      ],
      "involves": [
        "122496007",
        "297179000"
      ]
    },
    {
      "code": "202794003",
      "name": "Lumbar spondylosis",
      "pref_label": "Lumbar Spondylosis",
      "alt_labels": [
        "lumbar osteoarthritis",
        "lumbar degenerative disc disease"
      ],
      "involves": [
        "122496007",
        "297179000",
        "244944005"
      ]
    }
  ],
  "lumbar_edges": [
    {
      "from": "297179000",
      "to": "122496007",
      "relation": "part-of"
    },
    {
      "from": "11944003",
      "to": "122496007",
      "relation": "part-of"
    },
    {
      "from": "46467000",
      "to": "122496007",
      "relation": "part-of"
    },
    {
      "from": "244944005",
      "to": "122496007",
      "relation": "part-of"
    },
    {
      "from": "77736006",
      "to": "122496007",
      "relation": "part-of"
    },
    {
      "from": "279039007",
      "to": "122496007",
      "relation": "involves"
    },
    {
      "from": "279039007",
      "to": "297179000",
      "relation": "involves"
    },
    {
      "from": "202794003",
      "to": "122496007",
      "relation": "involves"
    },
    {
      "from": "202794003",
      "to": "297179000",
      "relation": "involves"
    },
    {
      "from": "202794003",
      "to": "244944005",
      "relation": "involves"
    }
  ],
  "api_validated": true,
  "api_concept_name": "Knee joint structure"
}